XiguandeLiliang/README.md
XiguandeLiliang/__init__.py
XiguandeLiliang/__main__.py
XiguandeLiliang/file.epub
XiguandeLiliang/index.html
XiguandeLiliang/css/__init__.py
XiguandeLiliang/css/annotations.css
XiguandeLiliang/css/main.css
XiguandeLiliang/css/normalize.css
XiguandeLiliang/css/popup.css
XiguandeLiliang/font/__init__.py
XiguandeLiliang/font/fontello.eot
XiguandeLiliang/font/fontello.svg
XiguandeLiliang/font/fontello.ttf
XiguandeLiliang/font/fontello.woff
XiguandeLiliang/img/__init__.py
XiguandeLiliang/img/annotator-glyph-sprite.png
XiguandeLiliang/img/annotator-icon-sprite.png
XiguandeLiliang/img/apple-touch-icon.png
XiguandeLiliang/img/cancelfullscreen.png
XiguandeLiliang/img/close.png
XiguandeLiliang/img/fullscreen.png
XiguandeLiliang/img/loader.gif
XiguandeLiliang/img/menu-icon.png
XiguandeLiliang/img/save.png
XiguandeLiliang/img/saved.png
XiguandeLiliang/img/settings-s.png
XiguandeLiliang/img/settings.png
XiguandeLiliang/img/star.png
XiguandeLiliang/js/__init__.py
XiguandeLiliang/js/epub.js
XiguandeLiliang/js/epub.min.js
XiguandeLiliang/js/epub.min.map
XiguandeLiliang/js/hooks.min.js
XiguandeLiliang/js/hooks.min.map
XiguandeLiliang/js/reader.js
XiguandeLiliang/js/reader.js.map
XiguandeLiliang/js/reader.min.js
XiguandeLiliang/js/reader.min.map
XiguandeLiliang/js/hooks/__init__.py
XiguandeLiliang/js/hooks/extensions/__init__.py
XiguandeLiliang/js/hooks/extensions/highlight.js
XiguandeLiliang/js/libs/__init__.py
XiguandeLiliang/js/libs/jquery.min.js
XiguandeLiliang/js/libs/localforage.min.js
XiguandeLiliang/js/libs/screenfull.js
XiguandeLiliang/js/libs/screenfull.min.js
XiguandeLiliang/js/libs/zip.min.js
XiguandeLiliang/js/plugins/__init__.py
XiguandeLiliang/js/plugins/hypothesis.js
XiguandeLiliang/js/plugins/search.js
xiguande_liliang-2022.10.15.0.dist-info/METADATA
xiguande_liliang-2022.10.15.0.dist-info/WHEEL
xiguande_liliang-2022.10.15.0.dist-info/entry_points.txt
xiguande_liliang-2022.10.15.0.dist-info/top_level.txt
xiguande_liliang-2022.10.15.0.dist-info/RECORD
